aioworkers_consul/__init__.py
aioworkers_consul/config.ini
aioworkers_consul/py.typed
aioworkers_consul-0.2.0.dist-info/METADATA
aioworkers_consul-0.2.0.dist-info/WHEEL
aioworkers_consul-0.2.0.dist-info/entry_points.txt
aioworkers_consul-0.2.0.dist-info/licenses/LICENSE
aioworkers_consul-0.2.0.dist-info/RECORD
