Metadata-Version: 2.1
Name: aioworkers-consul
Version: 0.2.0
Summary: aioworkers plugin for consul
Project-URL: Homepage, https://github.com/aioworkers/aioworkers-consul
Project-URL: Documentation, https://github.com/aioworkers/aioworkers-consul#readme
Project-URL: Issues, https://github.com/aioworkers/aioworkers-consul/issues
Project-URL: Source, https://github.com/aioworkers/aioworkers-consul
Author-email: Alexander Malev <malev@somedev.ru>
License-Expression: Apache-2.0
License-File: LICENSE
Keywords: aioworkers
Classifier: Development Status :: 5 - Production/Stable
Classifier: Framework :: AsyncIO
Classifier: Intended Audience :: Developers
Classifier: License :: OSI Approved :: Apache Software License
Classifier: Programming Language :: Python :: 3
Classifier: Programming Language :: Python :: 3 :: Only
Classifier: Programming Language :: Python :: 3.7
Classifier: Programming Language :: Python :: 3.8
Classifier: Programming Language :: Python :: 3.9
Classifier: Programming Language :: Python :: 3.10
Classifier: Programming Language :: Python :: 3.11
Classifier: Programming Language :: Python :: Implementation :: CPython
Classifier: Programming Language :: Python :: Implementation :: PyPy
Requires-Python: >=3.7
Requires-Dist: aioworkers>=0.21.1
Provides-Extra: dev-lint
Requires-Dist: black==23.7.0; extra == 'dev-lint'
Requires-Dist: isort==5.12.0; extra == 'dev-lint'
Requires-Dist: mypy==1.4.1; extra == 'dev-lint'
Requires-Dist: ruff==0.0.282; extra == 'dev-lint'
Provides-Extra: dev-test
Requires-Dist: aioworkers==0.26; extra == 'dev-test'
Requires-Dist: coverage[toml]==7.2.7; extra == 'dev-test'
Requires-Dist: pytest-aioworkers[asyncio]==0.4; extra == 'dev-test'
Requires-Dist: pytest-mock==3.11.1; extra == 'dev-test'
Requires-Dist: pytest==7.4.0; extra == 'dev-test'
Requires-Dist: pyyaml==6.0.1; extra == 'dev-test'
